boozelib.py
boozelib-0.7.0.dist-info/LICENSE.txt
boozelib-0.7.0.dist-info/WHEEL
boozelib-0.7.0.dist-info/METADATA
boozelib-0.7.0.dist-info/RECORD
