Metadata-Version: 2.1
Name: boozelib
Version: 0.7.0
Summary: A Python module containing a couple of tools to calculate the blood alcohol content of people.
